{"admin":{"pwd":"123456","addArr":[],"list":[{"name":"御龙源 北大荒酸菜棵500克×3袋 亲民有机酸菜棵 东北酸菜 笨酸菜  500g","id":"4777","checked":false,"price":"45.80","img":"http://www.lb717.com//public/upload/temp/2017/07-17/a1324f85faeab4bb134a74f5d9f1b1e4.jpg","count":2},{"name":"亲民食品 北大荒大荒亲民 高筋粉 5kg/袋","id":"4822","checked":false,"price":"55.80","img":"http://www.lb717.com//public/upload/temp/2017/04-19/de7ffdf03309a6927efc5706f4064c45.jpg","count":1}]},"xujianjing":{"pwd":"123","list":[{"name":"御龙源 北大荒酸菜棵500克×3袋 亲民有机酸菜棵 东北酸菜 笨酸菜  500g","id":"4777","checked":false,"price":"45.80","img":"http://www.lb717.com//public/upload/temp/2017/07-17/a1324f85faeab4bb134a74f5d9f1b1e4.jpg","count":1},{"name":"诗乡兔四川特产休闲兔肉零食50g多种口味麻辣小吃酱香大枣核桃味  50g","id":"4769","checked":false,"price":"12.00","img":"http://www.lb717.com//Uploads/images/admin/depositstoregoodsupload/release/0/2017-04/huge/3123730195.jpg","count":1}],"addArr":[{"id":0,"checked":false,"name":"范若宇","tel":"18203623892","cancel":"北京","city":"请选择市","area":"请选择区","myaddress":"我的"}]},"fanruoyu":{"pwd":"121212","addArr":[],"list":[]}}